python_xiso_repacker/__about__.py
python_xiso_repacker/__init__.py
python_xiso_repacker/__main__.py
python_xiso_repacker/util/__init__.py
python_xiso_repacker/util/extract_xiso.py
python_xiso_repacker/util/github.py
python_xiso_repacker-0.1.1.dist-info/METADATA
python_xiso_repacker-0.1.1.dist-info/WHEEL
python_xiso_repacker-0.1.1.dist-info/entry_points.txt
python_xiso_repacker-0.1.1.dist-info/licenses/LICENSE.txt
python_xiso_repacker-0.1.1.dist-info/RECORD
