Metadata-Version: 2.4
Name: python-xiso-repacker
Version: 0.1.1
Summary: Basic file replacer for xisos
Project-URL: Documentation, https://github.com/abaire/python-xiso-repacker#readme
Project-URL: Issues, https://github.com/abaire/python-xiso-repacker/issues
Project-URL: Source, https://github.com/abaire/python-xiso-repacker
Author-email: Erik Abair <erik.abair@bearbrains.work>
License-Expression: MIT
License-File: LICENSE.txt
Keywords: xbox,xemu,xiso
Classifier: Development Status :: 4 - Beta
Classifier: Programming Language :: Python
Classifier: Programming Language :: Python :: 3.9
Classifier: Programming Language :: Python :: 3.10
Classifier: Programming Language :: Python :: 3.11
Classifier: Programming Language :: Python :: 3.12
Classifier: Programming Language :: Python :: Implementation :: CPython
Classifier: Programming Language :: Python :: Implementation :: PyPy
Requires-Python: >=3.9
Requires-Dist: platformdirs~=4.3.6
Requires-Dist: requests~=2.32.3
